{"type": "Feature", "id": 22307044, "geometry": {"type": "Point", "coordinates": [15.06604, 37.474361]}, "properties": {"woe:id": 22307044, "woe:parent_id": 29343724, "woe:name": "Catania Fontanarossa Airport", "woe:placetype": 14, "woe:placetype_name": "Airport", "woe:lang": "ENG", "iso:country": "IT", "meta:provider": ["geoplanet:7.4.0", "geoplanet:7.4.1", "geoplanet:7.5.1", "geoplanet:7.5.2", "geoplanet:7.6.0", "geoplanet:7.8.1", "geoplanet:7.9.0", "geoplanet:7.10.0", "geoplanet:8.0.0", "woeplanet:8.0.0"], "meta:indexed": "2020-08-21T00:25:52.645281", "woe:alias_FIN_V": ["Catanian Lentokentta", "Catanian Lentokentt\u00e4"], "woe:alias_ENG_V": ["Catania City Airport", "CTA Airport", "CTA"], "woe:alias_ITA_V": ["Aeroporto Di Catania", "Aeroporto Filippo Eredia", "Aeroporto Fontanarossa", "Aeroporto CTA", "CTA Aeroporto"], "woe:alias_DAN_V": ["Catania Lufthavn"], "woe:alias_UNK_V": ["Letiste Catania", "Letisko Catania"], "woe:alias_DUT_V": ["Luchthaven Catania"], "woe:alias_POR_V": ["Aeroporto de Cat\u00e2nia", "Aeroporto de Catania"], "woe:alias_SWE_V": ["Catania Flygplats"], "meta:updated": "2020-10-14T11:16:42.457071", "woe:alias_ITA_Q": ["Aeroporto di Catania-Fontanarossa"], "woe:alias_GER_V": ["Flughafen Catania"], "woe:alias_FRE_V": ["A\u00e9roport de Catane", "Aeroport de Catane"], "woe:alias_SPA_V": ["Aeropuerto de Catania"], "woe:hierarchy": {"continent": 24865675, "country": 23424853, "town": 0, "planet": 1, "county": 12591830, "suburb": 0, "state": 7153344, "region": 0, "localadmin": 12676742}, "woe:timezone_id": 28350914, "woe:hash": "sqdtnvfzbpjw", "woe:centroid": [15.06604, 37.474361], "geom:latitude": 37.474361, "geom:longitude": 15.06604, "geom:hash": "sqdtnvfzbpjw", "woe:latitude": 37.474361, "geom:centroid": [15.06604, 37.474361], "woe:longitude": 15.06604, "woe:repo": "woeplanet-airport-it", "geom:area": 0.0, "woe:scale": 19}}