{"type": "Feature", "id": 12513858, "properties": {"woe:id": 12513858, "woe:parent_id": 726449, "woe:name": "Roma Urbe Airport", "woe:placetype": 14, "woe:placetype_name": "Airport", "woe:lang": "ITA", "iso:country": "IT", "meta:provider": ["geoplanet:7.3.1", "geoplanet:7.3.2", "geoplanet:7.4.0", "geoplanet:7.4.1", "geoplanet:7.5.1", "geoplanet:7.5.2", "geoplanet:7.6.0", "geoplanet:7.8.1", "geoplanet:7.9.0", "geoplanet:7.10.0", "geoplanet:8.0.0", "woeplanet:8.0.0"], "meta:indexed": "2020-08-20T20:20:34.323928", "meta:updated": "2020-08-22T02:30:21.527320", "woe:hierarchy": {"continent": 24865675, "country": 23424853, "town": 0, "planet": 1, "county": 12591802, "suburb": 0, "state": 7153336, "region": 0, "localadmin": 12675698}, "woe:timezone_id": 28350914, "woe:hash": "sr2ysmeu4ymr", "woe:centroid": [12.49673, 41.954762], "geom:latitude": 41.954762, "geom:longitude": 12.49673, "geom:hash": "sr2ysmeu4ymr", "woe:latitude": 41.954762, "geom:centroid": [12.49673, 41.954762], "woe:longitude": 12.49673, "woe:repo": "woeplanet-airport-it"}, "geometry": {"coordinates": [12.49673, 41.954762], "type": "Point"}}