{"type": "Feature", "id": 12513833, "geometry": {"type": "Point", "coordinates": [18.136101, 40.240799]}, "properties": {"woe:id": 12513833, "woe:parent_id": 714386, "woe:name": "Galatina Air Force Base", "woe:placetype": 14, "woe:placetype_name": "Airport", "woe:lang": "ENG", "iso:country": "IT", "meta:provider": ["geoplanet:7.3.1", "geoplanet:7.3.2", "geoplanet:7.4.0", "geoplanet:7.4.1", "geoplanet:7.5.1", "geoplanet:7.5.2", "geoplanet:7.6.0", "geoplanet:7.8.1", "geoplanet:7.9.0", "geoplanet:7.10.0", "geoplanet:8.0.0", "woeplanet:8.0.0"], "meta:indexed": "2020-08-20T20:20:34.316568", "woe:alias_ENG_V": ["Galatina Air", "Galatina Air Base", "Galatina Air Force", "Galatina Base", "Galatina Force", "Galatina Force Base", "LCC Airport", "LCC"], "woe:alias_ITA_V": ["Aeroporto LCC", "LCC Aeroporto"], "meta:updated": "2020-10-14T11:16:42.506578", "woe:hierarchy": {"continent": 24865675, "country": 23424853, "town": 0, "planet": 1, "county": 12591821, "suburb": 0, "state": 7153342, "region": 0, "localadmin": 12678794}, "woe:timezone_id": 28350914, "woe:hash": "srhuutw79u9h", "woe:centroid": [18.136101, 40.240799], "geom:latitude": 40.240799, "geom:longitude": 18.136101, "geom:hash": "srhuutw79u9h", "woe:latitude": 40.240799, "geom:centroid": [18.136101, 40.240799], "woe:longitude": 18.136101, "woe:repo": "woeplanet-airport-it", "geom:area": 0.0, "woe:scale": 19}}