{"type": "Feature", "id": 12513850, "properties": {"woe:id": 12513850, "woe:parent_id": 20141410, "woe:name": "Pisa Airport", "woe:placetype": 14, "woe:placetype_name": "Airport", "woe:lang": "ENG", "iso:country": "IT", "meta:provider": ["geoplanet:7.4.0", "geoplanet:7.4.1", "geoplanet:7.5.1", "geoplanet:7.5.2", "geoplanet:7.6.0", "geoplanet:7.8.1", "geoplanet:7.9.0", "geoplanet:7.10.0", "geoplanet:8.0.0", "woeplanet:8.0.0"], "meta:indexed": "2020-08-21T00:25:52.627622", "woe:alias_FIN_V": ["Galileo Galilei Lentokentt\u00e4", "Galileo Galilei Lentokentta"], "woe:alias_ENG_V": ["Galileo Galilei Airport", "PSA Airport", "PSA"], "woe:alias_ITA_V": ["Aeroporto Galileo Galilei", "Aeroporto Pisa", "Aeroporto San Giusto In Cannicci", "Aeroporto PSA", "PSA Aeroporto"], "woe:alias_DAN_V": ["Galileo Galilei Lufthavn"], "woe:alias_UNK_V": ["Letiste Galileo Galilei", "Letisko Galileo Galilei"], "woe:alias_DUT_V": ["Luchthaven Galileo Galilei"], "woe:alias_POR_V": ["Aeroporto Galileu Galilei"], "woe:alias_SWE_V": ["Galileo Galilei Flygplats"], "meta:updated": "2020-08-22T02:30:21.525760", "woe:alias_GER_V": ["Flughafen Galileo Galilei"], "woe:alias_FRE_V": ["A\u00e9roport Galileo Galilei", "Aeroport Galileo Galilei"], "woe:alias_SPA_V": ["Aeropuerto Galileo Galilei"], "woe:hierarchy": {"continent": 24865675, "country": 23424853, "town": 0, "planet": 1, "county": 12591867, "suburb": 0, "state": 7153345, "region": 0, "localadmin": 12676544}, "woe:timezone_id": 28350914, "woe:hash": "spz2seh5kdj3", "woe:centroid": [10.39876, 43.698689], "geom:latitude": 43.698689, "geom:longitude": 10.39876, "geom:hash": "spz2seh5kdj3", "woe:latitude": 43.698689, "geom:centroid": [10.39876, 43.698689], "woe:longitude": 10.39876, "woe:repo": "woeplanet-airport-it"}, "geometry": {"coordinates": [10.39876, 43.698689], "type": "Point"}}