{"type": "Feature", "id": 12513809, "properties": {"woe:id": 12513809, "woe:parent_id": 711799, "woe:name": "Cameri Airport", "woe:placetype": 14, "woe:placetype_name": "Airport", "woe:lang": "ENG", "iso:country": "IT", "meta:provider": ["geoplanet:7.3.1", "geoplanet:7.3.2", "geoplanet:7.4.0", "geoplanet:7.4.1", "geoplanet:7.5.1", "geoplanet:7.5.2", "geoplanet:7.6.0", "geoplanet:7.8.1", "geoplanet:7.9.0", "geoplanet:7.10.0", "geoplanet:8.0.0", "woeplanet:8.0.0"], "meta:indexed": "2020-08-20T20:20:34.309792", "meta:updated": "2020-08-22T02:30:21.520794", "woe:hierarchy": {"continent": 24865675, "country": 23424853, "town": 0, "planet": 1, "county": 12591859, "suburb": 0, "state": 7153341, "region": 0, "localadmin": 12677375}, "woe:timezone_id": 28350914, "woe:hash": "u0n5j2c698ux", "woe:centroid": [8.67, 45.531898], "geom:latitude": 45.531898, "geom:longitude": 8.67, "geom:hash": "u0n5j2c698ux", "woe:latitude": 45.531898, "geom:centroid": [8.67, 45.531898], "woe:longitude": 8.67, "woe:repo": "woeplanet-airport-it"}, "geometry": {"coordinates": [8.67, 45.531898], "type": "Point"}}