{"type": "Feature", "id": 12523918, "geometry": {"type": "Point", "coordinates": [14.3667, 40.616699]}, "properties": {"woe:id": 12523918, "woe:parent_id": 724362, "woe:name": "Sorrento Airport", "woe:placetype": 14, "woe:placetype_name": "Airport", "woe:lang": "ENG", "iso:country": "IT", "meta:provider": ["geoplanet:7.3.1", "geoplanet:7.3.2", "geoplanet:7.4.0", "geoplanet:7.4.1", "geoplanet:7.5.1", "geoplanet:7.5.2", "geoplanet:7.6.0", "geoplanet:7.8.1", "geoplanet:7.9.0", "geoplanet:7.10.0", "geoplanet:8.0.0", "woeplanet:8.0.0"], "meta:indexed": "2020-08-20T20:20:34.331839", "woe:alias_ENG_V": ["RRO Airport", "RRO"], "woe:alias_ITA_V": ["Aeroporto RRO", "RRO Aeroporto"], "meta:updated": "2020-10-14T11:16:42.470334", "woe:hierarchy": {"continent": 24865675, "country": 23424853, "town": 0, "planet": 1, "county": 12591829, "suburb": 0, "state": 7153333, "region": 0, "localadmin": 12682057}, "woe:timezone_id": 28350914, "woe:hash": "sr4pnfj92m7z", "woe:centroid": [14.3667, 40.616699], "geom:latitude": 40.616699, "geom:longitude": 14.3667, "geom:hash": "sr4pnfj92m7z", "woe:latitude": 40.616699, "geom:centroid": [14.3667, 40.616699], "woe:longitude": 14.3667, "woe:repo": "woeplanet-airport-it", "geom:area": 0.0, "woe:scale": 19}}